{
    "playerPuntingStatInfoList": [
        {
            "fullName": "A.Cole",
            "puntsBlocked": 0,
            "puntsIn20": 0,
            "puntLongest": 49,
            "puntTBs": 0,
            "puntNetYdsPerAtt": 47,
            "puntNetYds": 47,
            "puntAtt": 1,
            "puntYdsPerAtt": 49,
            "puntYds": 49,
            "rosterId": 551027191,
            "scheduleId": 543031347,
            "seasonIndex": 4,
            "statId": 545653440,
            "stageIndex": 1,
            "teamId": 759955486,
            "weekIndex": 0
        },
        {
            "fullName": "E.McPherson",
            "puntsBlocked": 0,
            "puntsIn20": 0,
            "puntLongest": 55,
            "puntTBs": 2,
            "puntNetYdsPerAtt": 46.6667,
            "puntNetYds": 140,
            "puntAtt": 3,
            "puntYdsPerAtt": 46.6667,
            "puntYds": 140,
            "rosterId": 551028511,
            "scheduleId": 543031350,
            "seasonIndex": 4,
            "statId": 545652805,
            "stageIndex": 1,
            "teamId": 759955458,
            "weekIndex": 0
        },
        {
            "fullName": "J.Horvath",
            "puntsBlocked": 0,
            "puntsIn20": 1,
            "puntLongest": 49,
            "puntTBs": 2,
            "puntNetYdsPerAtt": 46,
            "puntNetYds": 138,
            "puntAtt": 3,
            "puntYdsPerAtt": 46,
            "puntYds": 138,
            "rosterId": 551029761,
            "scheduleId": 543031350,
            "seasonIndex": 4,
            "statId": 545652990,
            "stageIndex": 1,
            "teamId": 759955459,
            "weekIndex": 0
        },
        {
            "fullName": "C.Little",
            "puntsBlocked": 0,
            "puntsIn20": 0,
            "puntLongest": 43,
            "puntTBs": 0,
            "puntNetYdsPerAtt": 39,
            "puntNetYds": 78,
            "puntAtt": 2,
            "puntYdsPerAtt": 37,
            "puntYds": 74,
            "rosterId": 551028330,
            "scheduleId": 543031351,
            "seasonIndex": 4,
            "statId": 545653719,
            "stageIndex": 1,
            "teamId": 759955477,
            "weekIndex": 0
        },
        {
            "fullName": "#.Bertrams",
            "puntsBlocked": 0,
            "puntsIn20": 1,
            "puntLongest": 66,
            "puntTBs": 2,
            "puntNetYdsPerAtt": 50,
            "puntNetYds": 250,
            "puntAtt": 5,
            "puntYdsPerAtt": 51.8,
            "puntYds": 259,
            "rosterId": 551027337,
            "scheduleId": 543031372,
            "seasonIndex": 4,
            "statId": 545652970,
            "stageIndex": 1,
            "teamId": 759955483,
            "weekIndex": 0
        },
        {
            "fullName": "J.Camarda",
            "puntsBlocked": 0,
            "puntsIn20": 0,
            "puntLongest": 61,
            "puntTBs": 1,
            "puntNetYdsPerAtt": 44.6667,
            "puntNetYds": 134,
            "puntAtt": 3,
            "puntYdsPerAtt": 47.6667,
            "puntYds": 143,
            "rosterId": 551027098,
            "scheduleId": 543031372,
            "seasonIndex": 4,
            "statId": 545653013,
            "stageIndex": 1,
            "teamId": 759955478,
            "weekIndex": 0
        },
        {
            "fullName": "R.Eckley",
            "puntsBlocked": 0,
            "puntsIn20": 0,
            "puntLongest": 47,
            "puntTBs": 0,
            "puntNetYdsPerAtt": 47,
            "puntNetYds": 47,
            "puntAtt": 1,
            "puntYdsPerAtt": 47,
            "puntYds": 47,
            "rosterId": 551027896,
            "scheduleId": 543031384,
            "seasonIndex": 4,
            "statId": 545652985,
            "stageIndex": 1,
            "teamId": 759955460,
            "weekIndex": 0
        },
        {
            "fullName": "M.Shipley",
            "puntsBlocked": 0,
            "puntsIn20": 0,
            "puntLongest": 30,
            "puntTBs": 0,
            "puntNetYdsPerAtt": 23.75,
            "puntNetYds": 95,
            "puntAtt": 4,
            "puntYdsPerAtt": 27,
            "puntYds": 108,
            "rosterId": 551029769,
            "scheduleId": 543031386,
            "seasonIndex": 4,
            "statId": 545653105,
            "stageIndex": 1,
            "teamId": 759955461,
            "weekIndex": 0
        },
        {
            "fullName": "C.Dicker",
            "puntsBlocked": 0,
            "puntsIn20": 0,
            "puntLongest": 64,
            "puntTBs": 2,
            "puntNetYdsPerAtt": 56,
            "puntNetYds": 168,
            "puntAtt": 3,
            "puntYdsPerAtt": 56,
            "puntYds": 168,
            "rosterId": 551027355,
            "scheduleId": 543031362,
            "seasonIndex": 4,
            "statId": 545653004,
            "stageIndex": 1,
            "teamId": 759955466,
            "weekIndex": 0
        },
        {
            "fullName": "M.Vassett",
            "puntsBlocked": 1,
            "puntsIn20": 0,
            "puntLongest": 60,
            "puntTBs": 2,
            "puntNetYdsPerAtt": 49,
            "puntNetYds": 147,
            "puntAtt": 3,
            "puntYdsPerAtt": 49,
            "puntYds": 147,
            "rosterId": 551030255,
            "scheduleId": 543031362,
            "seasonIndex": 4,
            "statId": 545653439,
            "stageIndex": 1,
            "teamId": 759955487,
            "weekIndex": 0
        },
        {
            "fullName": "R.Wright",
            "puntsBlocked": 0,
            "puntsIn20": 0,
            "puntLongest": 48,
            "puntTBs": 0,
            "puntNetYdsPerAtt": 48,
            "puntNetYds": 48,
            "puntAtt": 1,
            "puntYdsPerAtt": 48,
            "puntYds": 48,
            "rosterId": 551029733,
            "scheduleId": 543031365,
            "seasonIndex": 4,
            "statId": 545653738,
            "stageIndex": 1,
            "teamId": 759955482,
            "weekIndex": 0
        },
        {
            "fullName": "T.White",
            "puntsBlocked": 0,
            "puntsIn20": 1,
            "puntLongest": 43,
            "puntTBs": 0,
            "puntNetYdsPerAtt": 39.5,
            "puntNetYds": 79,
            "puntAtt": 2,
            "puntYdsPerAtt": 39,
            "puntYds": 78,
            "rosterId": 551028209,
            "scheduleId": 543031345,
            "seasonIndex": 4,
            "statId": 545653546,
            "stageIndex": 1,
            "teamId": 759955484,
            "weekIndex": 0
        },
        {
            "fullName": "J.Scott",
            "puntsBlocked": 0,
            "puntsIn20": 1,
            "puntLongest": 41,
            "puntTBs": 0,
            "puntNetYdsPerAtt": 41,
            "puntNetYds": 41,
            "puntAtt": 1,
            "puntYdsPerAtt": 41,
            "puntYds": 41,
            "rosterId": 551029091,
            "scheduleId": 543031371,
            "seasonIndex": 4,
            "statId": 545653588,
            "stageIndex": 1,
            "teamId": 759955488,
            "weekIndex": 0
        },
        {
            "fullName": "M.Turk",
            "puntsBlocked": 0,
            "puntsIn20": 0,
            "puntLongest": 37,
            "puntTBs": 0,
            "puntNetYdsPerAtt": 30,
            "puntNetYds": 30,
            "puntAtt": 1,
            "puntYdsPerAtt": 37,
            "puntYds": 37,
            "rosterId": 551029444,
            "scheduleId": 543031328,
            "seasonIndex": 4,
            "statId": 545653585,
            "stageIndex": 1,
            "teamId": 759955481,
            "weekIndex": 0
        },
        {
            "fullName": "D.Whelan",
            "puntsBlocked": 0,
            "puntsIn20": 0,
            "puntLongest": 40,
            "puntTBs": 0,
            "puntNetYdsPerAtt": 34,
            "puntNetYds": 34,
            "puntAtt": 1,
            "puntYdsPerAtt": 40,
            "puntYds": 40,
            "rosterId": 551029587,
            "scheduleId": 543031360,
            "seasonIndex": 4,
            "statId": 545652886,
            "stageIndex": 1,
            "teamId": 759955485,
            "weekIndex": 0
        },
        {
            "fullName": "A.Seibert",
            "puntsBlocked": 0,
            "puntsIn20": 0,
            "puntLongest": 42,
            "puntTBs": 0,
            "puntNetYdsPerAtt": 34,
            "puntNetYds": 102,
            "puntAtt": 3,
            "puntYdsPerAtt": 34,
            "puntYds": 102,
            "rosterId": 551029099,
            "scheduleId": 543031360,
            "seasonIndex": 4,
            "statId": 545653289,
            "stageIndex": 1,
            "teamId": 759955485,
            "weekIndex": 0
        }
    ],
    "message": "",
    "success": true
}