{
    "playerKickingStatInfoList": [
        {
            "kickPts": 0,
            "fGAtt": 1,
            "fG50PlusAtt": 0,
            "fG50PlusMade": 0,
            "fGLongest": 19,
            "fGMade": 1,
            "fGCompPct": 100,
            "fullName": "J.Crawshaw",
            "kickoffAtt": 7,
            "kickoffTBs": 4,
            "rosterId": 551030254,
            "scheduleId": 543031336,
            "seasonIndex": 4,
            "statId": 545653413,
            "stageIndex": 1,
            "teamId": 759955457,
            "weekIndex": 0,
            "xPAtt": 4,
            "xPMade": 3,
            "xPCompPct": 75
        },
        {
            "kickPts": 0,
            "fGAtt": 1,
            "fG50PlusAtt": 0,
            "fG50PlusMade": 0,
            "fGLongest": 0,
            "fGMade": 0,
            "fGCompPct": 0,
            "fullName": "J.Elliott",
            "kickoffAtt": 6,
            "kickoffTBs": 4,
            "rosterId": 551027456,
            "scheduleId": 543031336,
            "seasonIndex": 4,
            "statId": 545652791,
            "stageIndex": 1,
            "teamId": 759955472,
            "weekIndex": 0,
            "xPAtt": 1,
            "xPMade": 0,
            "xPCompPct": 0
        },
        {
            "kickPts": 0,
            "fGAtt": 3,
            "fG50PlusAtt": 0,
            "fG50PlusMade": 0,
            "fGLongest": 36,
            "fGMade": 3,
            "fGCompPct": 100,
            "fullName": "J.Browning",
            "kickoffAtt": 6,
            "kickoffTBs": 6,
            "rosterId": 551029810,
            "scheduleId": 543031343,
            "seasonIndex": 4,
            "statId": 545653694,
            "stageIndex": 1,
            "teamId": 759955479,
            "weekIndex": 0,
            "xPAtt": 6,
            "xPMade": 5,
            "xPCompPct": 83.3333
        },
        {
            "kickPts": 0,
            "fGAtt": 1,
            "fG50PlusAtt": 0,
            "fG50PlusMade": 0,
            "fGLongest": 26,
            "fGMade": 1,
            "fGCompPct": 100,
            "fullName": "L.Cooke",
            "kickoffAtt": 4,
            "kickoffTBs": 0,
            "rosterId": 551027222,
            "scheduleId": 543031343,
            "seasonIndex": 4,
            "statId": 545653274,
            "stageIndex": 1,
            "teamId": 759955470,
            "weekIndex": 0,
            "xPAtt": 0,
            "xPMade": 0,
            "xPCompPct": 0
        },
        {
            "kickPts": 0,
            "fGAtt": 0,
            "fG50PlusAtt": 0,
            "fG50PlusMade": 0,
            "fGLongest": 0,
            "fGMade": 0,
            "fGCompPct": 0,
            "fullName": "A.Cole",
            "kickoffAtt": 5,
            "kickoffTBs": 2,
            "rosterId": 551027191,
            "scheduleId": 543031347,
            "seasonIndex": 4,
            "statId": 545653440,
            "stageIndex": 1,
            "teamId": 759955486,
            "weekIndex": 0,
            "xPAtt": 0,
            "xPMade": 0,
            "xPCompPct": 0
        },
        {
            "kickPts": 0,
            "fGAtt": 2,
            "fG50PlusAtt": 1,
            "fG50PlusMade": 1,
            "fGLongest": 51,
            "fGMade": 2,
            "fGCompPct": 100,
            "fullName": "D.Lynch",
            "kickoffAtt": 0,
            "kickoffTBs": 0,
            "rosterId": 551027751,
            "scheduleId": 543031347,
            "seasonIndex": 4,
            "statId": 545653221,
            "stageIndex": 1,
            "teamId": 759955486,
            "weekIndex": 0,
            "xPAtt": 3,
            "xPMade": 3,
            "xPCompPct": 100
        },
        {
            "kickPts": 0,
            "fGAtt": 0,
            "fG50PlusAtt": 0,
            "fG50PlusMade": 0,
            "fGLongest": 0,
            "fGMade": 0,
            "fGCompPct": 0,
            "fullName": "H.Mevis",
            "kickoffAtt": 0,
            "kickoffTBs": 0,
            "rosterId": 551029782,
            "scheduleId": 543031347,
            "seasonIndex": 4,
            "statId": 545653074,
            "stageIndex": 1,
            "teamId": 759955471,
            "weekIndex": 0,
            "xPAtt": 3,
            "xPMade": 3,
            "xPCompPct": 100
        },
        {
            "kickPts": 0,
            "fGAtt": 2,
            "fG50PlusAtt": 1,
            "fG50PlusMade": 1,
            "fGLongest": 57,
            "fGMade": 2,
            "fGCompPct": 100,
            "fullName": "M.Araiza",
            "kickoffAtt": 5,
            "kickoffTBs": 4,
            "rosterId": 551026776,
            "scheduleId": 543031350,
            "seasonIndex": 4,
            "statId": 545653139,
            "stageIndex": 1,
            "teamId": 759955458,
            "weekIndex": 0,
            "xPAtt": 2,
            "xPMade": 2,
            "xPCompPct": 100
        },
        {
            "kickPts": 0,
            "fGAtt": 1,
            "fG50PlusAtt": 0,
            "fG50PlusMade": 0,
            "fGLongest": 23,
            "fGMade": 1,
            "fGCompPct": 100,
            "fullName": "J.Dalmas",
            "kickoffAtt": 0,
            "kickoffTBs": 0,
            "rosterId": 551030159,
            "scheduleId": 543031350,
            "seasonIndex": 4,
            "statId": 545653368,
            "stageIndex": 1,
            "teamId": 759955459,
            "weekIndex": 0,
            "xPAtt": 2,
            "xPMade": 2,
            "xPCompPct": 100
        },
        {
            "kickPts": 0,
            "fGAtt": 1,
            "fG50PlusAtt": 0,
            "fG50PlusMade": 0,
            "fGLongest": 24,
            "fGMade": 1,
            "fGCompPct": 100,
            "fullName": "G.Nicholson",
            "kickoffAtt": 7,
            "kickoffTBs": 0,
            "rosterId": 551030164,
            "scheduleId": 543031351,
            "seasonIndex": 4,
            "statId": 545652910,
            "stageIndex": 1,
            "teamId": 759955490,
            "weekIndex": 0,
            "xPAtt": 5,
            "xPMade": 5,
            "xPCompPct": 100
        },
        {
            "kickPts": 0,
            "fGAtt": 0,
            "fG50PlusAtt": 0,
            "fG50PlusMade": 0,
            "fGLongest": 0,
            "fGMade": 0,
            "fGCompPct": 0,
            "fullName": "C.Little",
            "kickoffAtt": 7,
            "kickoffTBs": 2,
            "rosterId": 551028330,
            "scheduleId": 543031351,
            "seasonIndex": 4,
            "statId": 545653719,
            "stageIndex": 1,
            "teamId": 759955477,
            "weekIndex": 0,
            "xPAtt": 5,
            "xPMade": 4,
            "xPCompPct": 80
        },
        {
            "kickPts": 0,
            "fGAtt": 0,
            "fG50PlusAtt": 0,
            "fG50PlusMade": 0,
            "fGLongest": 0,
            "fGMade": 0,
            "fGCompPct": 0,
            "fullName": "#.Bertrams",
            "kickoffAtt": 3,
            "kickoffTBs": 3,
            "rosterId": 551027337,
            "scheduleId": 543031372,
            "seasonIndex": 4,
            "statId": 545652970,
            "stageIndex": 1,
            "teamId": 759955483,
            "weekIndex": 0,
            "xPAtt": 0,
            "xPMade": 0,
            "xPCompPct": 0
        },
        {
            "kickPts": 0,
            "fGAtt": 0,
            "fG50PlusAtt": 0,
            "fG50PlusMade": 0,
            "fGLongest": 0,
            "fGMade": 0,
            "fGCompPct": 0,
            "fullName": "A.Birr",
            "kickoffAtt": 0,
            "kickoffTBs": 0,
            "rosterId": 551026721,
            "scheduleId": 543031372,
            "seasonIndex": 4,
            "statId": 545652978,
            "stageIndex": 1,
            "teamId": 759955483,
            "weekIndex": 0,
            "xPAtt": 2,
            "xPMade": 2,
            "xPCompPct": 100
        },
        {
            "kickPts": 0,
            "fGAtt": 0,
            "fG50PlusAtt": 0,
            "fG50PlusMade": 0,
            "fGLongest": 0,
            "fGMade": 0,
            "fGCompPct": 0,
            "fullName": "J.Camarda",
            "kickoffAtt": 3,
            "kickoffTBs": 2,
            "rosterId": 551027098,
            "scheduleId": 543031372,
            "seasonIndex": 4,
            "statId": 545653013,
            "stageIndex": 1,
            "teamId": 759955478,
            "weekIndex": 0,
            "xPAtt": 0,
            "xPMade": 0,
            "xPCompPct": 0
        },
        {
            "kickPts": 0,
            "fGAtt": 1,
            "fG50PlusAtt": 1,
            "fG50PlusMade": 0,
            "fGLongest": 0,
            "fGMade": 0,
            "fGCompPct": 0,
            "fullName": "J.Slye",
            "kickoffAtt": 0,
            "kickoffTBs": 0,
            "rosterId": 551029162,
            "scheduleId": 543031372,
            "seasonIndex": 4,
            "statId": 545652887,
            "stageIndex": 1,
            "teamId": 759955478,
            "weekIndex": 0,
            "xPAtt": 2,
            "xPMade": 1,
            "xPCompPct": 50
        },
        {
            "kickPts": 0,
            "fGAtt": 1,
            "fG50PlusAtt": 0,
            "fG50PlusMade": 0,
            "fGLongest": 47,
            "fGMade": 1,
            "fGCompPct": 100,
            "fullName": "T.Smack",
            "kickoffAtt": 8,
            "kickoffTBs": 8,
            "rosterId": 551028301,
            "scheduleId": 543031384,
            "seasonIndex": 4,
            "statId": 545653179,
            "stageIndex": 1,
            "teamId": 759955473,
            "weekIndex": 0,
            "xPAtt": 6,
            "xPMade": 6,
            "xPCompPct": 100
        },
        {
            "kickPts": 0,
            "fGAtt": 1,
            "fG50PlusAtt": 0,
            "fG50PlusMade": 0,
            "fGLongest": 49,
            "fGMade": 1,
            "fGCompPct": 100,
            "fullName": "J.Love",
            "kickoffAtt": 6,
            "kickoffTBs": 2,
            "rosterId": 551028123,
            "scheduleId": 543031384,
            "seasonIndex": 4,
            "statId": 545652742,
            "stageIndex": 1,
            "teamId": 759955460,
            "weekIndex": 0,
            "xPAtt": 4,
            "xPMade": 4,
            "xPCompPct": 100
        },
        {
            "kickPts": 0,
            "fGAtt": 1,
            "fG50PlusAtt": 0,
            "fG50PlusMade": 0,
            "fGLongest": 33,
            "fGMade": 1,
            "fGCompPct": 100,
            "fullName": "T.Bass",
            "kickoffAtt": 0,
            "kickoffTBs": 0,
            "rosterId": 551026855,
            "scheduleId": 543031386,
            "seasonIndex": 4,
            "statId": 545653722,
            "stageIndex": 1,
            "teamId": 759955475,
            "weekIndex": 0,
            "xPAtt": 1,
            "xPMade": 1,
            "xPCompPct": 100
        },
        {
            "kickPts": 0,
            "fGAtt": 0,
            "fG50PlusAtt": 0,
            "fG50PlusMade": 0,
            "fGLongest": 0,
            "fGMade": 0,
            "fGCompPct": 0,
            "fullName": "M.Shipley",
            "kickoffAtt": 8,
            "kickoffTBs": 1,
            "rosterId": 551029769,
            "scheduleId": 543031386,
            "seasonIndex": 4,
            "statId": 545653105,
            "stageIndex": 1,
            "teamId": 759955461,
            "weekIndex": 0,
            "xPAtt": 7,
            "xPMade": 7,
            "xPCompPct": 100
        },
        {
            "kickPts": 0,
            "fGAtt": 1,
            "fG50PlusAtt": 0,
            "fG50PlusMade": 0,
            "fGLongest": 19,
            "fGMade": 1,
            "fGCompPct": 100,
            "fullName": "C.Dicker",
            "kickoffAtt": 5,
            "kickoffTBs": 5,
            "rosterId": 551027355,
            "scheduleId": 543031362,
            "seasonIndex": 4,
            "statId": 545653004,
            "stageIndex": 1,
            "teamId": 759955466,
            "weekIndex": 0,
            "xPAtt": 3,
            "xPMade": 3,
            "xPCompPct": 100
        },
        {
            "kickPts": 0,
            "fGAtt": 0,
            "fG50PlusAtt": 0,
            "fG50PlusMade": 0,
            "fGLongest": 0,
            "fGMade": 0,
            "fGCompPct": 0,
            "fullName": "G.Crosa",
            "kickoffAtt": 0,
            "kickoffTBs": 0,
            "rosterId": 551030163,
            "scheduleId": 543031362,
            "seasonIndex": 4,
            "statId": 545653175,
            "stageIndex": 1,
            "teamId": 759955487,
            "weekIndex": 0,
            "xPAtt": 4,
            "xPMade": 4,
            "xPCompPct": 100
        },
        {
            "kickPts": 0,
            "fGAtt": 0,
            "fG50PlusAtt": 0,
            "fG50PlusMade": 0,
            "fGLongest": 0,
            "fGMade": 0,
            "fGCompPct": 0,
            "fullName": "H.Butker",
            "kickoffAtt": 8,
            "kickoffTBs": 2,
            "rosterId": 551027074,
            "scheduleId": 543031365,
            "seasonIndex": 4,
            "statId": 545653573,
            "stageIndex": 1,
            "teamId": 759955467,
            "weekIndex": 0,
            "xPAtt": 7,
            "xPMade": 7,
            "xPCompPct": 100
        },
        {
            "kickPts": 0,
            "fGAtt": 1,
            "fG50PlusAtt": 1,
            "fG50PlusMade": 0,
            "fGLongest": 0,
            "fGMade": 0,
            "fGCompPct": 0,
            "fullName": "J.Bates",
            "kickoffAtt": 2,
            "kickoffTBs": 0,
            "rosterId": 551028425,
            "scheduleId": 543031365,
            "seasonIndex": 4,
            "statId": 545652758,
            "stageIndex": 1,
            "teamId": 759955482,
            "weekIndex": 0,
            "xPAtt": 2,
            "xPMade": 2,
            "xPCompPct": 100
        },
        {
            "kickPts": 0,
            "fGAtt": 1,
            "fG50PlusAtt": 0,
            "fG50PlusMade": 0,
            "fGLongest": 48,
            "fGMade": 1,
            "fGCompPct": 100,
            "fullName": "B.Aubrey",
            "kickoffAtt": 6,
            "kickoffTBs": 0,
            "rosterId": 551026792,
            "scheduleId": 543031345,
            "seasonIndex": 4,
            "statId": 545653298,
            "stageIndex": 1,
            "teamId": 759955484,
            "weekIndex": 0,
            "xPAtt": 4,
            "xPMade": 4,
            "xPCompPct": 100
        },
        {
            "kickPts": 0,
            "fGAtt": 0,
            "fG50PlusAtt": 0,
            "fG50PlusMade": 0,
            "fGLongest": 0,
            "fGMade": 0,
            "fGCompPct": 0,
            "fullName": "A.Borregales",
            "kickoffAtt": 0,
            "kickoffTBs": 0,
            "rosterId": 551030161,
            "scheduleId": 543031345,
            "seasonIndex": 4,
            "statId": 545652802,
            "stageIndex": 1,
            "teamId": 759955489,
            "weekIndex": 0,
            "xPAtt": 2,
            "xPMade": 2,
            "xPCompPct": 100
        },
        {
            "kickPts": 0,
            "fGAtt": 0,
            "fG50PlusAtt": 0,
            "fG50PlusMade": 0,
            "fGLongest": 0,
            "fGMade": 0,
            "fGCompPct": 0,
            "fullName": "J.Scott",
            "kickoffAtt": 8,
            "kickoffTBs": 1,
            "rosterId": 551029091,
            "scheduleId": 543031371,
            "seasonIndex": 4,
            "statId": 545653588,
            "stageIndex": 1,
            "teamId": 759955488,
            "weekIndex": 0,
            "xPAtt": 0,
            "xPMade": 0,
            "xPCompPct": 0
        },
        {
            "kickPts": 0,
            "fGAtt": 2,
            "fG50PlusAtt": 0,
            "fG50PlusMade": 0,
            "fGLongest": 36,
            "fGMade": 2,
            "fGCompPct": 100,
            "fullName": "J.Karty",
            "kickoffAtt": 0,
            "kickoffTBs": 0,
            "rosterId": 551028190,
            "scheduleId": 543031371,
            "seasonIndex": 4,
            "statId": 545653025,
            "stageIndex": 1,
            "teamId": 759955488,
            "weekIndex": 0,
            "xPAtt": 4,
            "xPMade": 4,
            "xPCompPct": 100
        },
        {
            "kickPts": 0,
            "fGAtt": 0,
            "fG50PlusAtt": 0,
            "fG50PlusMade": 0,
            "fGLongest": 0,
            "fGMade": 0,
            "fGCompPct": 0,
            "fullName": "Y.Obeid",
            "kickoffAtt": 0,
            "kickoffTBs": 0,
            "rosterId": 551028826,
            "scheduleId": 543031371,
            "seasonIndex": 4,
            "statId": 545652806,
            "stageIndex": 1,
            "teamId": 759955456,
            "weekIndex": 0,
            "xPAtt": 3,
            "xPMade": 3,
            "xPCompPct": 100
        },
        {
            "kickPts": 0,
            "fGAtt": 0,
            "fG50PlusAtt": 0,
            "fG50PlusMade": 0,
            "fGLongest": 0,
            "fGMade": 0,
            "fGCompPct": 0,
            "fullName": "M.Palardy",
            "kickoffAtt": 0,
            "kickoffTBs": 0,
            "rosterId": 551029829,
            "scheduleId": 543031371,
            "seasonIndex": 4,
            "statId": 545653552,
            "stageIndex": 1,
            "teamId": 759955456,
            "weekIndex": 0,
            "xPAtt": 3,
            "xPMade": 3,
            "xPCompPct": 100
        },
        {
            "kickPts": 0,
            "fGAtt": 0,
            "fG50PlusAtt": 0,
            "fG50PlusMade": 0,
            "fGLongest": 0,
            "fGMade": 0,
            "fGCompPct": 0,
            "fullName": "M.Turk",
            "kickoffAtt": 9,
            "kickoffTBs": 1,
            "rosterId": 551029444,
            "scheduleId": 543031328,
            "seasonIndex": 4,
            "statId": 545653585,
            "stageIndex": 1,
            "teamId": 759955481,
            "weekIndex": 0,
            "xPAtt": 0,
            "xPMade": 0,
            "xPCompPct": 0
        },
        {
            "kickPts": 0,
            "fGAtt": 1,
            "fG50PlusAtt": 0,
            "fG50PlusMade": 0,
            "fGLongest": 22,
            "fGMade": 1,
            "fGCompPct": 100,
            "fullName": "P.Woodring",
            "kickoffAtt": 0,
            "kickoffTBs": 0,
            "rosterId": 551029151,
            "scheduleId": 543031328,
            "seasonIndex": 4,
            "statId": 545652796,
            "stageIndex": 1,
            "teamId": 759955481,
            "weekIndex": 0,
            "xPAtt": 7,
            "xPMade": 7,
            "xPCompPct": 100
        },
        {
            "kickPts": 0,
            "fGAtt": 2,
            "fG50PlusAtt": 0,
            "fG50PlusMade": 0,
            "fGLongest": 43,
            "fGMade": 2,
            "fGCompPct": 100,
            "fullName": "S.Shrader",
            "kickoffAtt": 8,
            "kickoffTBs": 7,
            "rosterId": 551029801,
            "scheduleId": 543031328,
            "seasonIndex": 4,
            "statId": 545653626,
            "stageIndex": 1,
            "teamId": 759955492,
            "weekIndex": 0,
            "xPAtt": 5,
            "xPMade": 5,
            "xPCompPct": 100
        },
        {
            "kickPts": 0,
            "fGAtt": 0,
            "fG50PlusAtt": 0,
            "fG50PlusMade": 0,
            "fGLongest": 0,
            "fGMade": 0,
            "fGCompPct": 0,
            "fullName": "T.Zentner",
            "kickoffAtt": 0,
            "kickoffTBs": 0,
            "rosterId": 551029757,
            "scheduleId": 543031328,
            "seasonIndex": 4,
            "statId": 545653224,
            "stageIndex": 1,
            "teamId": 759955492,
            "weekIndex": 0,
            "xPAtt": 1,
            "xPMade": 1,
            "xPCompPct": 100
        },
        {
            "kickPts": 0,
            "fGAtt": 0,
            "fG50PlusAtt": 0,
            "fG50PlusMade": 0,
            "fGLongest": 0,
            "fGMade": 0,
            "fGCompPct": 0,
            "fullName": "J.Ross",
            "kickoffAtt": 0,
            "kickoffTBs": 0,
            "rosterId": 551028194,
            "scheduleId": 543031349,
            "seasonIndex": 4,
            "statId": 545652883,
            "stageIndex": 1,
            "teamId": 759955468,
            "weekIndex": 0,
            "xPAtt": 2,
            "xPMade": 1,
            "xPCompPct": 50
        },
        {
            "kickPts": 0,
            "fGAtt": 0,
            "fG50PlusAtt": 0,
            "fG50PlusMade": 0,
            "fGLongest": 0,
            "fGMade": 0,
            "fGCompPct": 0,
            "fullName": "J.Sanders",
            "kickoffAtt": 5,
            "kickoffTBs": 0,
            "rosterId": 551029063,
            "scheduleId": 543031349,
            "seasonIndex": 4,
            "statId": 545652936,
            "stageIndex": 1,
            "teamId": 759955468,
            "weekIndex": 0,
            "xPAtt": 0,
            "xPMade": 0,
            "xPCompPct": 0
        },
        {
            "kickPts": 0,
            "fGAtt": 0,
            "fG50PlusAtt": 0,
            "fG50PlusMade": 0,
            "fGLongest": 0,
            "fGMade": 0,
            "fGCompPct": 0,
            "fullName": "W.Reichard",
            "kickoffAtt": 7,
            "kickoffTBs": 4,
            "rosterId": 551028942,
            "scheduleId": 543031349,
            "seasonIndex": 4,
            "statId": 545653683,
            "stageIndex": 1,
            "teamId": 759955491,
            "weekIndex": 0,
            "xPAtt": 5,
            "xPMade": 4,
            "xPCompPct": 80
        },
        {
            "kickPts": 0,
            "fGAtt": 1,
            "fG50PlusAtt": 0,
            "fG50PlusMade": 0,
            "fGLongest": 45,
            "fGMade": 1,
            "fGCompPct": 100,
            "fullName": "M.Bhaghani",
            "kickoffAtt": 9,
            "kickoffTBs": 3,
            "rosterId": 551026807,
            "scheduleId": 543031360,
            "seasonIndex": 4,
            "statId": 545653417,
            "stageIndex": 1,
            "teamId": 759955463,
            "weekIndex": 0,
            "xPAtt": 8,
            "xPMade": 8,
            "xPCompPct": 100
        },
        {
            "kickPts": 0,
            "fGAtt": 0,
            "fG50PlusAtt": 0,
            "fG50PlusMade": 0,
            "fGLongest": 0,
            "fGMade": 0,
            "fGCompPct": 0,
            "fullName": "D.Whelan",
            "kickoffAtt": 1,
            "kickoffTBs": 1,
            "rosterId": 551029587,
            "scheduleId": 543031360,
            "seasonIndex": 4,
            "statId": 545652886,
            "stageIndex": 1,
            "teamId": 759955485,
            "weekIndex": 0,
            "xPAtt": 0,
            "xPMade": 0,
            "xPCompPct": 0
        },
        {
            "kickPts": 0,
            "fGAtt": 1,
            "fG50PlusAtt": 1,
            "fG50PlusMade": 1,
            "fGLongest": 51,
            "fGMade": 1,
            "fGCompPct": 100,
            "fullName": "R.Rehkow",
            "kickoffAtt": 7,
            "kickoffTBs": 3,
            "rosterId": 551029335,
            "scheduleId": 543031367,
            "seasonIndex": 4,
            "statId": 545653608,
            "stageIndex": 1,
            "teamId": 759955462,
            "weekIndex": 0,
            "xPAtt": 5,
            "xPMade": 5,
            "xPCompPct": 100
        },
        {
            "kickPts": 0,
            "fGAtt": 2,
            "fG50PlusAtt": 1,
            "fG50PlusMade": 1,
            "fGLongest": 50,
            "fGMade": 2,
            "fGCompPct": 100,
            "fullName": "C.York",
            "kickoffAtt": 6,
            "kickoffTBs": 5,
            "rosterId": 551029743,
            "scheduleId": 543031367,
            "seasonIndex": 4,
            "statId": 545652973,
            "stageIndex": 1,
            "teamId": 759955469,
            "weekIndex": 0,
            "xPAtt": 3,
            "xPMade": 3,
            "xPCompPct": 100
        }
    ],
    "message": "",
    "success": true
}