{
    "playerDefensiveStatInfoList": [
        {
            "defCatchAllowed": 0,
            "defDeflections": 0,
            "defForcedFum": 0,
            "defFumRec": 0,
            "defInts": 2,
            "defIntReturnYds": 32,
            "defPts": 0,
            "defSacks": 0,
            "defSafeties": 0,
            "defTDs": 0,
            "defTotalTackles": 1,
            "fullName": "D.Lenoir",
            "rosterId": 551028306,
            "scheduleId": 543031369,
            "seasonIndex": 4,
            "statId": 543950017,
            "stageIndex": 1,
            "teamId": 759955456,
            "weekIndex": 1
        },
        {
            "defCatchAllowed": 0,
            "defDeflections": 0,
            "defForcedFum": 0,
            "defFumRec": 0,
            "defInts": 0,
            "defIntReturnYds": 0,
            "defPts": 0,
            "defSacks": 0,
            "defSafeties": 0,
            "defTDs": 0,
            "defTotalTackles": 1,
            "fullName": "T.Hufanga",
            "rosterId": 551027948,
            "scheduleId": 543031369,
            "seasonIndex": 4,
            "statId": 543960059,
            "stageIndex": 1,
            "teamId": 759955456,
            "weekIndex": 1
        },
        {
            "defCatchAllowed": 0,
            "defDeflections": 3,
            "defForcedFum": 0,
            "defFumRec": 0,
            "defInts": 0,
            "defIntReturnYds": 0,
            "defPts": 0,
            "defSacks": 0,
            "defSafeties": 0,
            "defTDs": 0,
            "defTotalTackles": 3,
            "fullName": "J.Brown",
            "rosterId": 551027023,
            "scheduleId": 543031369,
            "seasonIndex": 4,
            "statId": 543956125,
            "stageIndex": 1,
            "teamId": 759955456,
            "weekIndex": 1
        },
        {
            "defCatchAllowed": 0,
            "defDeflections": 0,
            "defForcedFum": 0,
            "defFumRec": 0,
            "defInts": 0,
            "defIntReturnYds": 0,
            "defPts": 0,
            "defSacks": 0,
            "defSafeties": 0,
            "defTDs": 0,
            "defTotalTackles": 2,
            "fullName": "R.Hallman",
            "rosterId": 551029913,
            "scheduleId": 543031369,
            "seasonIndex": 4,
            "statId": 543958344,
            "stageIndex": 1,
            "teamId": 759955456,
            "weekIndex": 1
        },
        {
            "defCatchAllowed": 0,
            "defDeflections": 0,
            "defForcedFum": 0,
            "defFumRec": 0,
            "defInts": 0,
            "defIntReturnYds": 0,
            "defPts": 0,
            "defSacks": 1.5,
            "defSafeties": 0,
            "defTDs": 0,
            "defTotalTackles": 3,
            "fullName": "D.Bailey",
            "rosterId": 551029931,
            "scheduleId": 543031369,
            "seasonIndex": 4,
            "statId": 543955485,
            "stageIndex": 1,
            "teamId": 759955456,
            "weekIndex": 1
        },
        {
            "defCatchAllowed": 0,
            "defDeflections": 0,
            "defForcedFum": 0,
            "defFumRec": 0,
            "defInts": 0,
            "defIntReturnYds": 0,
            "defPts": 0,
            "defSacks": 0,
            "defSafeties": 0,
            "defTDs": 0,
            "defTotalTackles": 2,
            "fullName": "T.Tuipulotu",
            "rosterId": 551029439,
            "scheduleId": 543031369,
            "seasonIndex": 4,
            "statId": 543951877,
            "stageIndex": 1,
            "teamId": 759955456,
            "weekIndex": 1
        },
        {
            "defCatchAllowed": 0,
            "defDeflections": 1,
            "defForcedFum": 0,
            "defFumRec": 0,
            "defInts": 0,
            "defIntReturnYds": 0,
            "defPts": 0,
            "defSacks": 0,
            "defSafeties": 0,
            "defTDs": 0,
            "defTotalTackles": 0,
            "fullName": "J.Parrish",
            "rosterId": 551027685,
            "scheduleId": 543031369,
            "seasonIndex": 4,
            "statId": 543954117,
            "stageIndex": 1,
            "teamId": 759955456,
            "weekIndex": 1
        },
        {
            "defCatchAllowed": 0,
            "defDeflections": 1,
            "defForcedFum": 0,
            "defFumRec": 0,
            "defInts": 0,
            "defIntReturnYds": 0,
            "defPts": 0,
            "defSacks": 0,
            "defSafeties": 0,
            "defTDs": 0,
            "defTotalTackles": 1,
            "fullName": "C.Epps",
            "rosterId": 551027866,
            "scheduleId": 543031369,
            "seasonIndex": 4,
            "statId": 543957425,
            "stageIndex": 1,
            "teamId": 759955456,
            "weekIndex": 1
        },
        {
            "defCatchAllowed": 0,
            "defDeflections": 0,
            "defForcedFum": 0,
            "defFumRec": 0,
            "defInts": 0,
            "defIntReturnYds": 0,
            "defPts": 0,
            "defSacks": 0,
            "defSafeties": 0,
            "defTDs": 0,
            "defTotalTackles": 2,
            "fullName": "J.Williams",
            "rosterId": 551027905,
            "scheduleId": 543031369,
            "seasonIndex": 4,
            "statId": 543960976,
            "stageIndex": 1,
            "teamId": 759955456,
            "weekIndex": 1
        },
        {
            "defCatchAllowed": 0,
            "defDeflections": 0,
            "defForcedFum": 0,
            "defFumRec": 0,
            "defInts": 0,
            "defIntReturnYds": 0,
            "defPts": 0,
            "defSacks": 0.5,
            "defSafeties": 0,
            "defTDs": 0,
            "defTotalTackles": 3,
            "fullName": "D.Stephens II",
            "rosterId": 551030284,
            "scheduleId": 543031369,
            "seasonIndex": 4,
            "statId": 543957483,
            "stageIndex": 1,
            "teamId": 759955456,
            "weekIndex": 1
        },
        {
            "defCatchAllowed": 0,
            "defDeflections": 0,
            "defForcedFum": 0,
            "defFumRec": 0,
            "defInts": 1,
            "defIntReturnYds": 52,
            "defPts": 0,
            "defSacks": 0,
            "defSafeties": 0,
            "defTDs": 0,
            "defTotalTackles": 0,
            "fullName": "O.Chambliss",
            "rosterId": 551027212,
            "scheduleId": 543031369,
            "seasonIndex": 4,
            "statId": 543960393,
            "stageIndex": 1,
            "teamId": 759955456,
            "weekIndex": 1
        },
        {
            "defCatchAllowed": 0,
            "defDeflections": 0,
            "defForcedFum": 0,
            "defFumRec": 0,
            "defInts": 2,
            "defIntReturnYds": 220,
            "defPts": 0,
            "defSacks": 0,
            "defSafeties": 0,
            "defTDs": 0,
            "defTotalTackles": 1,
            "fullName": "T.Arnold",
            "rosterId": 551026787,
            "scheduleId": 543031369,
            "seasonIndex": 4,
            "statId": 543955461,
            "stageIndex": 1,
            "teamId": 759955479,
            "weekIndex": 1
        },
        {
            "defCatchAllowed": 0,
            "defDeflections": 1,
            "defForcedFum": 0,
            "defFumRec": 0,
            "defInts": 1,
            "defIntReturnYds": 19,
            "defPts": 0,
            "defSacks": 0,
            "defSafeties": 0,
            "defTDs": 0,
            "defTotalTackles": 2,
            "fullName": "E.Rakestraw Jr",
            "rosterId": 551028911,
            "scheduleId": 543031369,
            "seasonIndex": 4,
            "statId": 543949489,
            "stageIndex": 1,
            "teamId": 759955479,
            "weekIndex": 1
        },
        {
            "defCatchAllowed": 0,
            "defDeflections": 1,
            "defForcedFum": 1,
            "defFumRec": 0,
            "defInts": 3,
            "defIntReturnYds": 27,
            "defPts": 0,
            "defSacks": 0,
            "defSafeties": 0,
            "defTDs": 0,
            "defTotalTackles": 2,
            "fullName": "J.Campbell",
            "rosterId": 551027104,
            "scheduleId": 543031369,
            "seasonIndex": 4,
            "statId": 543955464,
            "stageIndex": 1,
            "teamId": 759955479,
            "weekIndex": 1
        },
        {
            "defCatchAllowed": 0,
            "defDeflections": 0,
            "defForcedFum": 0,
            "defFumRec": 0,
            "defInts": 1,
            "defIntReturnYds": 31,
            "defPts": 0,
            "defSacks": 0,
            "defSafeties": 0,
            "defTDs": 0,
            "defTotalTackles": 1,
            "fullName": "B.Branch",
            "rosterId": 551026974,
            "scheduleId": 543031369,
            "seasonIndex": 4,
            "statId": 543960570,
            "stageIndex": 1,
            "teamId": 759955479,
            "weekIndex": 1
        },
        {
            "defCatchAllowed": 0,
            "defDeflections": 0,
            "defForcedFum": 0,
            "defFumRec": 0,
            "defInts": 1,
            "defIntReturnYds": 10,
            "defPts": 0,
            "defSacks": 0,
            "defSafeties": 0,
            "defTDs": 0,
            "defTotalTackles": 5,
            "fullName": "T.Hunter",
            "rosterId": 551029868,
            "scheduleId": 543031369,
            "seasonIndex": 4,
            "statId": 557711453,
            "stageIndex": 1,
            "teamId": 759955479,
            "weekIndex": 1
        },
        {
            "defCatchAllowed": 0,
            "defDeflections": 0,
            "defForcedFum": 0,
            "defFumRec": 0,
            "defInts": 0,
            "defIntReturnYds": 0,
            "defPts": 0,
            "defSacks": 0,
            "defSafeties": 0,
            "defTDs": 0,
            "defTotalTackles": 4,
            "fullName": "L.Campbell",
            "rosterId": 551027853,
            "scheduleId": 543031369,
            "seasonIndex": 4,
            "statId": 543955361,
            "stageIndex": 1,
            "teamId": 759955479,
            "weekIndex": 1
        },
        {
            "defCatchAllowed": 0,
            "defDeflections": 0,
            "defForcedFum": 0,
            "defFumRec": 0,
            "defInts": 0,
            "defIntReturnYds": 0,
            "defPts": 0,
            "defSacks": 1,
            "defSafeties": 0,
            "defTDs": 0,
            "defTotalTackles": 1,
            "fullName": "A.Adebawore",
            "rosterId": 551029022,
            "scheduleId": 543031369,
            "seasonIndex": 4,
            "statId": 543959564,
            "stageIndex": 1,
            "teamId": 759955479,
            "weekIndex": 1
        },
        {
            "defCatchAllowed": 0,
            "defDeflections": 0,
            "defForcedFum": 0,
            "defFumRec": 0,
            "defInts": 1,
            "defIntReturnYds": 24,
            "defPts": 0,
            "defSacks": 0,
            "defSafeties": 0,
            "defTDs": 1,
            "defTotalTackles": 0,
            "fullName": "W.Weeks",
            "rosterId": 551029504,
            "scheduleId": 543031369,
            "seasonIndex": 4,
            "statId": 543956143,
            "stageIndex": 1,
            "teamId": 759955479,
            "weekIndex": 1
        },
        {
            "defCatchAllowed": 0,
            "defDeflections": 0,
            "defForcedFum": 0,
            "defFumRec": 0,
            "defInts": 1,
            "defIntReturnYds": 3,
            "defPts": 0,
            "defSacks": 0,
            "defSafeties": 0,
            "defTDs": 0,
            "defTotalTackles": 0,
            "fullName": "L.Carter",
            "rosterId": 551028656,
            "scheduleId": 543031369,
            "seasonIndex": 4,
            "statId": 543951510,
            "stageIndex": 1,
            "teamId": 759955479,
            "weekIndex": 1
        },
        {
            "defCatchAllowed": 0,
            "defDeflections": 0,
            "defForcedFum": 0,
            "defFumRec": 0,
            "defInts": 0,
            "defIntReturnYds": 0,
            "defPts": 0,
            "defSacks": 0,
            "defSafeties": 0,
            "defTDs": 0,
            "defTotalTackles": 2,
            "fullName": "T.Still",
            "rosterId": 551029256,
            "scheduleId": 543031369,
            "seasonIndex": 4,
            "statId": 543951240,
            "stageIndex": 1,
            "teamId": 759955479,
            "weekIndex": 1
        },
        {
            "defCatchAllowed": 0,
            "defDeflections": 0,
            "defForcedFum": 0,
            "defFumRec": 1,
            "defInts": 0,
            "defIntReturnYds": 0,
            "defPts": 0,
            "defSacks": 0,
            "defSafeties": 0,
            "defTDs": 0,
            "defTotalTackles": 0,
            "fullName": "L.Arrington Jr",
            "rosterId": 551029410,
            "scheduleId": 543031369,
            "seasonIndex": 4,
            "statId": 543952577,
            "stageIndex": 1,
            "teamId": 759955479,
            "weekIndex": 1
        },
        {
            "defCatchAllowed": 0,
            "defDeflections": 0,
            "defForcedFum": 0,
            "defFumRec": 0,
            "defInts": 0,
            "defIntReturnYds": 0,
            "defPts": 0,
            "defSacks": 0,
            "defSafeties": 0,
            "defTDs": 0,
            "defTotalTackles": 1,
            "fullName": "T.Walker",
            "rosterId": 551029517,
            "scheduleId": 543031358,
            "seasonIndex": 4,
            "statId": 543956274,
            "stageIndex": 1,
            "teamId": 759955477,
            "weekIndex": 1
        },
        {
            "defCatchAllowed": 0,
            "defDeflections": 1,
            "defForcedFum": 0,
            "defFumRec": 0,
            "defInts": 0,
            "defIntReturnYds": 0,
            "defPts": 0,
            "defSacks": 0,
            "defSafeties": 0,
            "defTDs": 0,
            "defTotalTackles": 2,
            "fullName": "T.Davis",
            "rosterId": 551029915,
            "scheduleId": 543031358,
            "seasonIndex": 4,
            "statId": 543954275,
            "stageIndex": 1,
            "teamId": 759955477,
            "weekIndex": 1
        },
        {
            "defCatchAllowed": 0,
            "defDeflections": 0,
            "defForcedFum": 0,
            "defFumRec": 0,
            "defInts": 0,
            "defIntReturnYds": 0,
            "defPts": 0,
            "defSacks": 0,
            "defSafeties": 0,
            "defTDs": 0,
            "defTotalTackles": 1,
            "fullName": "T.Quinn",
            "rosterId": 551028202,
            "scheduleId": 543031358,
            "seasonIndex": 4,
            "statId": 543949500,
            "stageIndex": 1,
            "teamId": 759955477,
            "weekIndex": 1
        },
        {
            "defCatchAllowed": 0,
            "defDeflections": 0,
            "defForcedFum": 0,
            "defFumRec": 0,
            "defInts": 0,
            "defIntReturnYds": 0,
            "defPts": 0,
            "defSacks": 0,
            "defSafeties": 0,
            "defTDs": 0,
            "defTotalTackles": 2,
            "fullName": "L.Patterson",
            "rosterId": 551026946,
            "scheduleId": 543031358,
            "seasonIndex": 4,
            "statId": 543952893,
            "stageIndex": 1,
            "teamId": 759955477,
            "weekIndex": 1
        },
        {
            "defCatchAllowed": 0,
            "defDeflections": 0,
            "defForcedFum": 0,
            "defFumRec": 0,
            "defInts": 0,
            "defIntReturnYds": 0,
            "defPts": 0,
            "defSacks": 1,
            "defSafeties": 0,
            "defTDs": 0,
            "defTotalTackles": 1,
            "fullName": "K.Crawford",
            "rosterId": 551027423,
            "scheduleId": 543031358,
            "seasonIndex": 4,
            "statId": 543956025,
            "stageIndex": 1,
            "teamId": 759955477,
            "weekIndex": 1
        },
        {
            "defCatchAllowed": 0,
            "defDeflections": 0,
            "defForcedFum": 1,
            "defFumRec": 0,
            "defInts": 0,
            "defIntReturnYds": 0,
            "defPts": 0,
            "defSacks": 0,
            "defSafeties": 0,
            "defTDs": 0,
            "defTotalTackles": 0,
            "fullName": "*.Riddick",
            "rosterId": 551027103,
            "scheduleId": 543031358,
            "seasonIndex": 4,
            "statId": 543949877,
            "stageIndex": 1,
            "teamId": 759955477,
            "weekIndex": 1
        },
        {
            "defCatchAllowed": 0,
            "defDeflections": 0,
            "defForcedFum": 0,
            "defFumRec": 0,
            "defInts": 0,
            "defIntReturnYds": 0,
            "defPts": 0,
            "defSacks": 0,
            "defSafeties": 0,
            "defTDs": 0,
            "defTotalTackles": 2,
            "fullName": "J.McDonald",
            "rosterId": 551027844,
            "scheduleId": 543031358,
            "seasonIndex": 4,
            "statId": 543951850,
            "stageIndex": 1,
            "teamId": 759955477,
            "weekIndex": 1
        },
        {
            "defCatchAllowed": 0,
            "defDeflections": 0,
            "defForcedFum": 0,
            "defFumRec": 0,
            "defInts": 0,
            "defIntReturnYds": 0,
            "defPts": 0,
            "defSacks": 0,
            "defSafeties": 0,
            "defTDs": 0,
            "defTotalTackles": 5,
            "fullName": "A.McLaughlin",
            "rosterId": 551027245,
            "scheduleId": 543031358,
            "seasonIndex": 4,
            "statId": 543956020,
            "stageIndex": 1,
            "teamId": 759955477,
            "weekIndex": 1
        },
        {
            "defCatchAllowed": 0,
            "defDeflections": 0,
            "defForcedFum": 0,
            "defFumRec": 0,
            "defInts": 0,
            "defIntReturnYds": 0,
            "defPts": 0,
            "defSacks": 0,
            "defSafeties": 0,
            "defTDs": 0,
            "defTotalTackles": 4,
            "fullName": "Q.Mitchell",
            "rosterId": 551028559,
            "scheduleId": 543031358,
            "seasonIndex": 4,
            "statId": 543957553,
            "stageIndex": 1,
            "teamId": 759955477,
            "weekIndex": 1
        },
        {
            "defCatchAllowed": 0,
            "defDeflections": 0,
            "defForcedFum": 0,
            "defFumRec": 0,
            "defInts": 0,
            "defIntReturnYds": 0,
            "defPts": 0,
            "defSacks": 0,
            "defSafeties": 0,
            "defTDs": 0,
            "defTotalTackles": 1,
            "fullName": "E.Forbes Jr",
            "rosterId": 551027546,
            "scheduleId": 543031358,
            "seasonIndex": 4,
            "statId": 543960867,
            "stageIndex": 1,
            "teamId": 759955477,
            "weekIndex": 1
        },
        {
            "defCatchAllowed": 0,
            "defDeflections": 0,
            "defForcedFum": 0,
            "defFumRec": 0,
            "defInts": 0,
            "defIntReturnYds": 0,
            "defPts": 0,
            "defSacks": 1,
            "defSafeties": 0,
            "defTDs": 0,
            "defTotalTackles": 2,
            "fullName": "B.Browning",
            "rosterId": 551027038,
            "scheduleId": 543031358,
            "seasonIndex": 4,
            "statId": 543956863,
            "stageIndex": 1,
            "teamId": 759955477,
            "weekIndex": 1
        },
        {
            "defCatchAllowed": 0,
            "defDeflections": 0,
            "defForcedFum": 0,
            "defFumRec": 0,
            "defInts": 0,
            "defIntReturnYds": 0,
            "defPts": 0,
            "defSacks": 0,
            "defSafeties": 0,
            "defTDs": 0,
            "defTotalTackles": 1,
            "fullName": "A.Isaac",
            "rosterId": 551027989,
            "scheduleId": 543031358,
            "seasonIndex": 4,
            "statId": 543955418,
            "stageIndex": 1,
            "teamId": 759955477,
            "weekIndex": 1
        },
        {
            "defCatchAllowed": 0,
            "defDeflections": 0,
            "defForcedFum": 0,
            "defFumRec": 0,
            "defInts": 0,
            "defIntReturnYds": 0,
            "defPts": 0,
            "defSacks": 0,
            "defSafeties": 0,
            "defTDs": 0,
            "defTotalTackles": 2,
            "fullName": "A.Adams",
            "rosterId": 551026722,
            "scheduleId": 543031358,
            "seasonIndex": 4,
            "statId": 543957252,
            "stageIndex": 1,
            "teamId": 759955477,
            "weekIndex": 1
        },
        {
            "defCatchAllowed": 0,
            "defDeflections": 0,
            "defForcedFum": 0,
            "defFumRec": 0,
            "defInts": 1,
            "defIntReturnYds": 69,
            "defPts": 0,
            "defSacks": 0,
            "defSafeties": 0,
            "defTDs": 1,
            "defTotalTackles": 4,
            "fullName": "R.Green",
            "rosterId": 551027709,
            "scheduleId": 543031358,
            "seasonIndex": 4,
            "statId": 543954170,
            "stageIndex": 1,
            "teamId": 759955477,
            "weekIndex": 1
        },
        {
            "defCatchAllowed": 0,
            "defDeflections": 0,
            "defForcedFum": 0,
            "defFumRec": 0,
            "defInts": 0,
            "defIntReturnYds": 0,
            "defPts": 0,
            "defSacks": 0,
            "defSafeties": 0,
            "defTDs": 0,
            "defTotalTackles": 1,
            "fullName": "T.Nubin",
            "rosterId": 551028689,
            "scheduleId": 543031358,
            "seasonIndex": 4,
            "statId": 543949123,
            "stageIndex": 1,
            "teamId": 759955477,
            "weekIndex": 1
        },
        {
            "defCatchAllowed": 0,
            "defDeflections": 0,
            "defForcedFum": 0,
            "defFumRec": 0,
            "defInts": 0,
            "defIntReturnYds": 0,
            "defPts": 0,
            "defSacks": 0,
            "defSafeties": 0,
            "defTDs": 0,
            "defTotalTackles": 1,
            "fullName": "M.Crosby",
            "rosterId": 551027258,
            "scheduleId": 543031358,
            "seasonIndex": 4,
            "statId": 543958295,
            "stageIndex": 1,
            "teamId": 759955484,
            "weekIndex": 1
        },
        {
            "defCatchAllowed": 0,
            "defDeflections": 1,
            "defForcedFum": 0,
            "defFumRec": 0,
            "defInts": 0,
            "defIntReturnYds": 0,
            "defPts": 0,
            "defSacks": 0,
            "defSafeties": 0,
            "defTDs": 0,
            "defTotalTackles": 1,
            "fullName": "N.Hobbs",
            "rosterId": 551027892,
            "scheduleId": 543031358,
            "seasonIndex": 4,
            "statId": 543949543,
            "stageIndex": 1,
            "teamId": 759955484,
            "weekIndex": 1
        },
        {
            "defCatchAllowed": 0,
            "defDeflections": 0,
            "defForcedFum": 0,
            "defFumRec": 0,
            "defInts": 1,
            "defIntReturnYds": 33,
            "defPts": 0,
            "defSacks": 0,
            "defSafeties": 0,
            "defTDs": 0,
            "defTotalTackles": 2,
            "fullName": "T.Moehrig",
            "rosterId": 551028564,
            "scheduleId": 543031358,
            "seasonIndex": 4,
            "statId": 543959283,
            "stageIndex": 1,
            "teamId": 759955484,
            "weekIndex": 1
        },
        {
            "defCatchAllowed": 0,
            "defDeflections": 0,
            "defForcedFum": 0,
            "defFumRec": 0,
            "defInts": 0,
            "defIntReturnYds": 0,
            "defPts": 0,
            "defSacks": 0,
            "defSafeties": 0,
            "defTDs": 0,
            "defTotalTackles": 2,
            "fullName": "J.Reid",
            "rosterId": 551028944,
            "scheduleId": 543031358,
            "seasonIndex": 4,
            "statId": 543954972,
            "stageIndex": 1,
            "teamId": 759955484,
            "weekIndex": 1
        },
        {
            "defCatchAllowed": 0,
            "defDeflections": 1,
            "defForcedFum": 0,
            "defFumRec": 0,
            "defInts": 1,
            "defIntReturnYds": 16,
            "defPts": 0,
            "defSacks": 0,
            "defSafeties": 0,
            "defTDs": 0,
            "defTotalTackles": 2,
            "fullName": "B.Morrison",
            "rosterId": 551029887,
            "scheduleId": 543031358,
            "seasonIndex": 4,
            "statId": 543957682,
            "stageIndex": 1,
            "teamId": 759955484,
            "weekIndex": 1
        },
        {
            "defCatchAllowed": 0,
            "defDeflections": 0,
            "defForcedFum": 0,
            "defFumRec": 0,
            "defInts": 0,
            "defIntReturnYds": 0,
            "defPts": 0,
            "defSacks": 1.5,
            "defSafeties": 0,
            "defTDs": 0,
            "defTotalTackles": 1,
            "fullName": "T.Williams",
            "rosterId": 551029932,
            "scheduleId": 543031358,
            "seasonIndex": 4,
            "statId": 543955308,
            "stageIndex": 1,
            "teamId": 759955484,
            "weekIndex": 1
        },
        {
            "defCatchAllowed": 0,
            "defDeflections": 0,
            "defForcedFum": 0,
            "defFumRec": 0,
            "defInts": 0,
            "defIntReturnYds": 0,
            "defPts": 0,
            "defSacks": 0,
            "defSafeties": 0,
            "defTDs": 0,
            "defTotalTackles": 1,
            "fullName": "T.Parker",
            "rosterId": 551030057,
            "scheduleId": 543031358,
            "seasonIndex": 4,
            "statId": 543952449,
            "stageIndex": 1,
            "teamId": 759955484,
            "weekIndex": 1
        },
        {
            "defCatchAllowed": 0,
            "defDeflections": 0,
            "defForcedFum": 0,
            "defFumRec": 0,
            "defInts": 0,
            "defIntReturnYds": 0,
            "defPts": 0,
            "defSacks": 0,
            "defSafeties": 0,
            "defTDs": 0,
            "defTotalTackles": 2,
            "fullName": "E.Hausmann",
            "rosterId": 551029128,
            "scheduleId": 543031358,
            "seasonIndex": 4,
            "statId": 543957902,
            "stageIndex": 1,
            "teamId": 759955484,
            "weekIndex": 1
        },
        {
            "defCatchAllowed": 0,
            "defDeflections": 0,
            "defForcedFum": 0,
            "defFumRec": 0,
            "defInts": 0,
            "defIntReturnYds": 0,
            "defPts": 0,
            "defSacks": 0,
            "defSafeties": 0,
            "defTDs": 0,
            "defTotalTackles": 1,
            "fullName": "S.Hartzell",
            "rosterId": 551029096,
            "scheduleId": 543031358,
            "seasonIndex": 4,
            "statId": 543950777,
            "stageIndex": 1,
            "teamId": 759955484,
            "weekIndex": 1
        },
        {
            "defCatchAllowed": 0,
            "defDeflections": 0,
            "defForcedFum": 1,
            "defFumRec": 0,
            "defInts": 0,
            "defIntReturnYds": 0,
            "defPts": 0,
            "defSacks": 2,
            "defSafeties": 0,
            "defTDs": 0,
            "defTotalTackles": 2,
            "fullName": "K.Viliamu-Asa",
            "rosterId": 551028818,
            "scheduleId": 543031358,
            "seasonIndex": 4,
            "statId": 543960432,
            "stageIndex": 1,
            "teamId": 759955484,
            "weekIndex": 1
        },
        {
            "defCatchAllowed": 0,
            "defDeflections": 1,
            "defForcedFum": 0,
            "defFumRec": 0,
            "defInts": 0,
            "defIntReturnYds": 0,
            "defPts": 0,
            "defSacks": 0,
            "defSafeties": 0,
            "defTDs": 0,
            "defTotalTackles": 2,
            "fullName": "K.Mack",
            "rosterId": 551029263,
            "scheduleId": 543031358,
            "seasonIndex": 4,
            "statId": 543958050,
            "stageIndex": 1,
            "teamId": 759955484,
            "weekIndex": 1
        },
        {
            "defCatchAllowed": 0,
            "defDeflections": 2,
            "defForcedFum": 0,
            "defFumRec": 0,
            "defInts": 0,
            "defIntReturnYds": 0,
            "defPts": 0,
            "defSacks": 0.5,
            "defSafeties": 0,
            "defTDs": 0,
            "defTotalTackles": 2,
            "fullName": "J.Gibbens",
            "rosterId": 551027635,
            "scheduleId": 543031358,
            "seasonIndex": 4,
            "statId": 543949406,
            "stageIndex": 1,
            "teamId": 759955484,
            "weekIndex": 1
        },
        {
            "defCatchAllowed": 0,
            "defDeflections": 0,
            "defForcedFum": 0,
            "defFumRec": 0,
            "defInts": 1,
            "defIntReturnYds": 0,
            "defPts": 0,
            "defSacks": 1,
            "defSafeties": 0,
            "defTDs": 0,
            "defTotalTackles": 3,
            "fullName": "C.Braswell",
            "rosterId": 551026976,
            "scheduleId": 543031358,
            "seasonIndex": 4,
            "statId": 543956338,
            "stageIndex": 1,
            "teamId": 759955484,
            "weekIndex": 1
        },
        {
            "defCatchAllowed": 0,
            "defDeflections": 0,
            "defForcedFum": 0,
            "defFumRec": 0,
            "defInts": 0,
            "defIntReturnYds": 0,
            "defPts": 0,
            "defSacks": 0,
            "defSafeties": 0,
            "defTDs": 0,
            "defTotalTackles": 1,
            "fullName": "D.Robinson",
            "rosterId": 551028994,
            "scheduleId": 543031358,
            "seasonIndex": 4,
            "statId": 543953968,
            "stageIndex": 1,
            "teamId": 759955484,
            "weekIndex": 1
        },
        {
            "defCatchAllowed": 0,
            "defDeflections": 2,
            "defForcedFum": 0,
            "defFumRec": 0,
            "defInts": 1,
            "defIntReturnYds": 1,
            "defPts": 0,
            "defSacks": 0,
            "defSafeties": 0,
            "defTDs": 0,
            "defTotalTackles": 0,
            "fullName": "J.Ramsey",
            "rosterId": 551028914,
            "scheduleId": 543031358,
            "seasonIndex": 4,
            "statId": 543960974,
            "stageIndex": 1,
            "teamId": 759955484,
            "weekIndex": 1
        }
    ],
    "message": "",
    "success": true
}